mylivebox/__init__.py
mylivebox/client.py
mylivebox/entities.py
mylivebox-0.0.2.dist-info/LICENSE
mylivebox-0.0.2.dist-info/METADATA
mylivebox-0.0.2.dist-info/WHEEL
mylivebox-0.0.2.dist-info/top_level.txt
mylivebox-0.0.2.dist-info/RECORD
