Metadata-Version: 2.1
Name: mylivebox
Version: 0.0.2
Summary: Access Livebox data and perform basic operations
Home-page: https://github.com/jean-edouard-boulanger/mylivebox
Author: Jean-Edouard Boulanger
Author-email: jean.edouard.boulanger@gmail.com
License: MIT
Platform: UNKNOWN
Classifier: Development Status :: 4 - Beta
Classifier: License :: OSI Approved :: MIT License
Classifier: Operating System :: OS Independent
Requires-Python: >=3.6
Requires-Dist: requests
